{
  "project_info": {
    "project_number": "139710716773",
    "project_id": "kiitconnects",
    "storage_bucket": "kiitconnects.appspot.com"
  },
  "client": [
    {
      "client_info": {
        "mobilesdk_app_id": "1:139710716773:android:ae888ee96c3eac328fdf8c",
        "android_client_info": {
          "package_name": "com.kiit.kiit_connect"
        }
      },
      "oauth_client": [
        {
          "client_id": "139710716773-t5l6inselttl07h7napbi53ou3r2c4cp.apps.googleusercontent.com",
          "client_type": 3
        }
      ],
      "api_key": [
        {
          "current_key": "AIzaSyBpCg7_YFVex1nLcQJQqaGbf_-_Q17AUL0"
        }
      ],
      "services": {
        "appinvite_service": {
          "other_platform_oauth_client": [
            {
              "client_id": "139710716773-t5l6inselttl07h7napbi53ou3r2c4cp.apps.googleusercontent.com",
              "client_type": 3
            }
          ]
        }
      }
    }
  ],
  "configuration_version": "1"
}